api/__init__.py
api/api_call.py
payrun-0.0.1.dist-info/LICENSE
payrun-0.0.1.dist-info/METADATA
payrun-0.0.1.dist-info/WHEEL
payrun-0.0.1.dist-info/top_level.txt
payrun-0.0.1.dist-info/RECORD
