Metadata-Version: 2.1
Name: payrun
Version: 0.0.1
Summary: A Python SDK for PayRun API
Home-page: https://github.com/pypa/sampleproject
Author: Andrii Pushkar
Author-email: zingeon1@gmail.com
License: UNKNOWN
Platform: UNKNOWN
Classifier: Programming Language :: Python :: 3
Classifier: License :: OSI Approved :: MIT License
Classifier: Operating System :: OS Independent
Requires-Python: >=3.6
